testify/__init__.py
testify/assertions.py
testify/compat.py
testify/deprecated_assertions.py
testify/errors.py
testify/exceptions.py
testify/exit.py
testify/test_case.py
testify/test_discovery.py
testify/test_fixtures.py
testify/test_logger.py
testify/test_program.py
testify/test_reporter.py
testify/test_rerunner.py
testify/test_result.py
testify/test_runner.py
testify/test_runner_json_replay.py
testify/contrib/__init__.py
testify/contrib/doctestcase.py
testify/plugins/__init__.py
testify/plugins/json_log.py
testify/plugins/profile.py
testify/plugins/seed.py
testify/plugins/test_case_time_log.py
testify/utils/__init__.py
testify/utils/class_logger.py
testify/utils/exception.py
testify/utils/inspection.py
testify/utils/mock_logging.py
testify/utils/stringdiffer.py
testify/utils/tempdir.py
testify/utils/turtle.py
testify-0.11.0.data/scripts/testify
testify-0.11.0.dist-info/DESCRIPTION.rst
testify-0.11.0.dist-info/METADATA
testify-0.11.0.dist-info/RECORD
testify-0.11.0.dist-info/WHEEL
testify-0.11.0.dist-info/metadata.json
testify-0.11.0.dist-info/pbr.json
testify-0.11.0.dist-info/top_level.txt
