Metadata-Version: 1.1
Name: testify
Version: 0.11.0
Summary: Testing framework
Home-page: http://github.com/Yelp/Testify
Author: Yelp
Author-email: yelplabs@yelp.com
License: UNKNOWN
Platform: UNKNOWN
Classifier: Programming Language :: Python
Classifier: Programming Language :: Python :: 2
Classifier: Programming Language :: Python :: 2.7
Classifier: Programming Language :: Python :: 3
Classifier: Programming Language :: Python :: 3.4
Classifier: Programming Language :: Python :: 3.5
Classifier: Programming Language :: Python :: Implementation :: CPython
Classifier: Operating System :: OS Independent
Classifier: License :: OSI Approved :: Apache Software License
Classifier: Topic :: Software Development :: Testing
Classifier: Intended Audience :: Developers
Classifier: Development Status :: 4 - Beta
Provides: testify
